deepevent/__init__.py
deepevent/__main__.py
deepevent/deepevent.py
deepevent/utils.py
deepevent/data/DeepEventModel.json
deepevent-0.4.dist-info/METADATA
deepevent-0.4.dist-info/WHEEL
deepevent-0.4.dist-info/entry_points.txt
deepevent-0.4.dist-info/top_level.txt
deepevent-0.4.dist-info/RECORD
