Metadata-Version: 2.1
Name: deepevent
Version: 0.4
Summary: Deep Learning to identify gait events
Home-page: UNKNOWN
Author: Lempereur Mathieu
Author-email: mathieu.lempereur@univ-brest.fr
License: UNKNOWN
Platform: UNKNOWN
Classifier: Programming Language :: Python
Classifier: Programming Language :: Python :: 3.7
Classifier: Operating System :: Microsoft :: Windows
Classifier: Natural Language :: English
Requires-Dist: tensorflow (>=2.1.0)
Requires-Dist: keras (>=2.3.1)
Requires-Dist: numpy (>=1.18.1)
Requires-Dist: scipy (>=1.4.1)
Requires-Dist: pyBTK (>=0.1.1)
Requires-Dist: googledrivedownloader (==0.4)
